mbedmgr/__init__.py
mbedmgr/embeddings_manager.py
mbedmgr/website_source.py
mbedmgr-0.0.1.dist-info/METADATA
mbedmgr-0.0.1.dist-info/WHEEL
mbedmgr-0.0.1.dist-info/top_level.txt
mbedmgr-0.0.1.dist-info/RECORD
