Metadata-Version: 2.1
Name: mbedmgr
Version: 0.0.1
Requires-Dist: beautifulsoup4 ==4.12.2
Requires-Dist: lxml ==4.9.3
Requires-Dist: requests ==2.31.0
